Metadata-Version: 1.1
Name: SimpleComplexCalculator
Version: 0.0.2
Summary: Calculateur simple entre nombres complexes
Home-page: UNKNOWN
Author: Tom Ebermeyer
Author-email: tom.ebermeyer@cpe.fr
License: UNKNOWN
Platform: UNKNOWN
Classifier: Programming Language :: Python :: 3
Classifier: Operating System :: OS Independent
